LICENSE.rst
MANIFEST.in
README.rst
octo.py
requirements.txt
setup.py
docs/Makefile
docs/conf.py
docs/index.rst
docs/license.rst
docs/modules.rst
docs/octo.rst
docs/_build/doctrees/environment.pickle
docs/_build/doctrees/index.doctree
docs/_build/doctrees/license.doctree
docs/_build/doctrees/modules.doctree
docs/_build/doctrees/octo.doctree
docs/_build/html/.buildinfo
docs/_build/html/genindex.html
docs/_build/html/index.html
docs/_build/html/license.html
docs/_build/html/modules.html
docs/_build/html/objects.inv
docs/_build/html/octo.html
docs/_build/html/py-modindex.html
docs/_build/html/search.html
docs/_build/html/searchindex.js
docs/_build/html/_modules/index.html
docs/_build/html/_modules/octo/cli.html
docs/_build/html/_modules/octo/exceptions.html
docs/_build/html/_modules/octo/manager.html
docs/_build/html/_modules/octo/plugin.html
docs/_build/html/_sources/index.txt
docs/_build/html/_sources/license.txt
docs/_build/html/_sources/modules.txt
docs/_build/html/_sources/octo.txt
docs/_build/html/_static/ajax-loader.gif
docs/_build/html/_static/basic.css
docs/_build/html/_static/comment-bright.png
docs/_build/html/_static/comment-close.png
docs/_build/html/_static/comment.png
docs/_build/html/_static/default.css
docs/_build/html/_static/doctools.js
docs/_build/html/_static/down-pressed.png
docs/_build/html/_static/down.png
docs/_build/html/_static/file.png
docs/_build/html/_static/jquery.js
docs/_build/html/_static/minus.png
docs/_build/html/_static/plus.png
docs/_build/html/_static/pygments.css
docs/_build/html/_static/searchtools.js
docs/_build/html/_static/sidebar.js
docs/_build/html/_static/underscore.js
docs/_build/html/_static/up-pressed.png
docs/_build/html/_static/up.png
docs/_build/html/_static/websupport.js
octo/__init__.py
octo/cli.py
octo/exceptions.py
octo/manager.py
octo/plugin.py
octo/version
octo.egg-info/PKG-INFO
octo.egg-info/SOURCES.txt
octo.egg-info/dependency_links.txt
octo.egg-info/entry_points.txt
octo.egg-info/requires.txt
octo.egg-info/top_level.txt