Metadata-Version: 1.1
Name: octo
Version: 0.3.0
Summary: A plugin framework which allows you to write your application as a collection of (optionally interconnected) plugins.
Home-page: http://octo.zoni.nl
Author: Nick Groenen
Author-email: zoni@zoni.nl
License: License :: OSI Approved :: BSD License
Platform: UNKNOWN
Classifier: Environment :: Plugins
Classifier: Topic :: Software Development :: Libraries :: Application Frameworks
Classifier: Development Status :: 4 - Beta
Classifier: Operating System :: POSIX :: Linux
Classifier: Programming Language :: Python
Classifier: Programming Language :: Python :: 2.7
Classifier: Programming Language :: Python :: 3
Classifier: Topic :: Software Development
Classifier: Topic :: Utilities
